{
  "main": {
    "da": {
      "identity": {
        "version": {
          "@cldrVersion": "23.1",
          "@number": "$Revision: 8671 $"
        },
        "generation": {
          "@date": "$Date: 2013-05-03 14:17:48 -0500 (Fri, 03 May 2013) $"
        },
        "language": "da"
      },
      "localeDisplayNames": {
        "variants": {
          "1901": "traditionel tysk retskrivning",
          "1994": "1994",
          "1996": "tysk retskrivning fra 1996",
          "1606NICT": "1606NICT",
          "1694ACAD": "1694ACAD",
          "1959ACAD": "1959ACAD",
          "ALALC97": "ALALC97",
          "ALUKU": "ALUKU",
          "AREVELA": "østarmensk",
          "AREVMDA": "vestarmensk",
          "BAKU1926": "BAKU1926",
          "BAUDDHA": "BAUDDHA",
          "BISCAYAN": "BISCAYAN",
          "BISKE": "BISKE",
          "BOHORIC": "BOHORIC",
          "BOONT": "boontling",
          "DAJNKO": "DAJNKO",
          "EMODENG": "EMODENG",
          "FONIPA": "det internationale fonetiske alfabet",
          "FONUPA": "det uraliske fonetiske alfabet",
          "FONXSAMP": "FONXSAMP",
          "HEPBURN": "HEPBURN",
          "HOGNORSK": "HOGNORSK",
          "ITIHASA": "ITIHASA",
          "JAUER": "JAUER",
          "JYUTPING": "JYUTPING",
          "KKCOR": "KKCOR",
          "KSCOR": "KSCOR",
          "LAUKIKA": "LAUKIKA",
          "LIPAW": "lipovaz",
          "LUNA1918": "LUNA1918",
          "METELKO": "METELKO",
          "MONOTON": "monotonisk",
          "NDYUKA": "NDYUKA",
          "NEDIS": "NEDIS",
          "NJIVA": "NJIVA",
          "NULIK": "NULIK",
          "OSOJS": "OSOJS",
          "PAMAKA": "PAMAKA",
          "PETR1708": "PETR1708",
          "PINYIN": "pinyin",
          "POLYTON": "polytonisk",
          "POSIX": "computer",
          "PUTER": "PUTER",
          "REVISED": "revideret retskrivning",
          "RIGIK": "RIGIK",
          "ROZAJ": "ROZAJ",
          "RUMGR": "RUMGR",
          "SAAHO": "SAAHO",
          "SCOTLAND": "skotsk standardengelsk",
          "SCOUSE": "SCOUSE",
          "SOLBA": "SOLBA",
          "SURMIRAN": "SURMIRAN",
          "SURSILV": "SURSILV",
          "SUTSILV": "SUTSILV",
          "TARASK": "TARASK",
          "UCCOR": "UCCOR",
          "UCRCOR": "UCRCOR",
          "ULSTER": "ULSTER",
          "VAIDIKA": "VAIDIKA",
          "VALENCIA": "VALENCIA",
          "VALLADER": "VALLADER",
          "WADEGILE": "Wade-Giles"
        }
      }
    }
  }
}
