{
  "main": {
    "tig-ER": {
      "identity": {
        "version": {
          "_cldrVersion": "25",
          "_number": "$Revision: 91 $"
        },
        "generation": {
          "_date": "$Date: 2014-03-13 22:27:12 -0500 (Thu, 13 Mar 2014) $"
        },
        "language": "root",
        "territory": "ER"
      },
      "localeDisplayNames": {
        "territories": {
          "001": "001",
          "002": "002",
          "003": "003",
          "005": "005",
          "009": "009",
          "011": "011",
          "013": "013",
          "014": "014",
          "015": "015",
          "017": "017",
          "018": "018",
          "019": "019",
          "021": "021",
          "029": "029",
          "030": "030",
          "034": "034",
          "035": "035",
          "039": "039",
          "053": "053",
          "054": "054",
          "057": "057",
          "061": "061",
          "142": "142",
          "143": "143",
          "145": "145",
          "150": "150",
          "151": "151",
          "154": "154",
          "155": "155",
          "419": "419",
          "AC": "AC",
          "AD": "አንዶራ",
          "AE": "የተባበሩት አረብ ኤምሬትስ",
          "AF": "AF",
          "AG": "AG",
          "AI": "AI",
          "AL": "አልባኒያ",
          "AM": "አርሜኒያ",
          "AN": "ኔዘርላንድስ አንቲልስ",
          "AO": "AO",
          "AQ": "AQ",
          "AR": "አርጀንቲና",
          "AS": "AS",
          "AT": "ኦስትሪያ",
          "AU": "አውስትሬሊያ",
          "AW": "AW",
          "AX": "AX",
          "AZ": "አዘርባጃን",
          "BA": "ቦስኒያ እና ሄርዞጎቪኒያ",
          "BB": "ባርቤዶስ",
          "BD": "BD",
          "BE": "ቤልጄም",
          "BF": "BF",
          "BG": "ቡልጌሪያ",
          "BH": "ባህሬን",
          "BI": "BI",
          "BJ": "BJ",
          "BL": "BL",
          "BM": "ቤርሙዳ",
          "BN": "BN",
          "BO": "ቦሊቪያ",
          "BQ": "BQ",
          "BR": "ብራዚል",
          "BS": "BS",
          "BT": "ቡህታን",
          "BV": "BV",
          "BW": "BW",
          "BY": "ቤላሩስ",
          "BZ": "ቤሊዘ",
          "CA": "CA",
          "CC": "CC",
          "CD": "ኮንጎ",
          "CD-alt-variant": "CD",
          "CF": "የመካከለኛው አፍሪካ ሪፐብሊክ",
          "CG": "CG",
          "CG-alt-variant": "CG",
          "CH": "ስዊዘርላንድ",
          "CI": "CI",
          "CI-alt-variant": "CI",
          "CK": "CK",
          "CL": "ቺሊ",
          "CM": "ካሜሩን",
          "CN": "ቻይና",
          "CO": "ኮሎምቢያ",
          "CP": "CP",
          "CR": "CR",
          "CU": "CU",
          "CV": "ኬፕ ቬርዴ",
          "CW": "CW",
          "CX": "CX",
          "CY": "ሳይፕረስ",
          "CZ": "ቼክ ሪፑብሊክ",
          "DE": "ጀርመን",
          "DG": "DG",
          "DJ": "DJ",
          "DK": "ዴንማርክ",
          "DM": "ዶሚኒካ",
          "DO": "ዶሚኒክ ሪፑብሊክ",
          "DZ": "አልጄሪያ",
          "EA": "EA",
          "EC": "ኢኳዶር",
          "EE": "ኤስቶኒያ",
          "EG": "ግብጽ",
          "EH": "ምዕራባዊ ሳህራ",
          "ER": "ኤርትራ",
          "ES": "ስፔን",
          "ET": "ኢትዮጵያ",
          "EU": "EU",
          "FI": "ፊንላንድ",
          "FJ": "ፊጂ",
          "FK": "FK",
          "FK-alt-variant": "FK",
          "FM": "ሚክሮኔዢያ",
          "FO": "FO",
          "FR": "ፈረንሳይ",
          "GA": "GA",
          "GB": "እንግሊዝ",
          "GB-alt-short": "GB",
          "GD": "GD",
          "GE": "ጆርጂያ",
          "GF": "የፈረንሳይ ጉዊአና",
          "GG": "GG",
          "GH": "GH",
          "GI": "GI",
          "GL": "GL",
          "GM": "ጋምቢያ",
          "GN": "ጊኒ",
          "GP": "GP",
          "GQ": "ኢኳቶሪያል ጊኒ",
          "GR": "ግሪክ",
          "GS": "GS",
          "GT": "GT",
          "GU": "GU",
          "GW": "ቢሳዎ",
          "GY": "ጉያና",
          "HK": "ሆንግ ኮንግ",
          "HK-alt-short": "HK",
          "HM": "HM",
          "HN": "HN",
          "HR": "ክሮኤሽያ",
          "HT": "ሀይቲ",
          "HU": "ሀንጋሪ",
          "IC": "IC",
          "ID": "ኢንዶኔዢያ",
          "IE": "አየርላንድ",
          "IL": "እስራኤል",
          "IM": "IM",
          "IN": "ህንድ",
          "IO": "IO",
          "IQ": "ኢራቅ",
          "IR": "IR",
          "IS": "አይስላንድ",
          "IT": "ጣሊያን",
          "JE": "JE",
          "JM": "ጃማይካ",
          "JO": "ጆርዳን",
          "JP": "ጃፓን",
          "KE": "KE",
          "KG": "KG",
          "KH": "ካምቦዲያ",
          "KI": "KI",
          "KM": "ኮሞሮስ",
          "KN": "KN",
          "KP": "ደቡብ ኮሪያ",
          "KR": "ሰሜን ኮሪያ",
          "KW": "ክዌት",
          "KY": "KY",
          "KZ": "KZ",
          "LA": "LA",
          "LB": "ሊባኖስ",
          "LC": "LC",
          "LI": "LI",
          "LK": "LK",
          "LR": "LR",
          "LS": "LS",
          "LT": "ሊቱዌኒያ",
          "LU": "LU",
          "LV": "ላትቪያ",
          "LY": "ሊቢያ",
          "MA": "ሞሮኮ",
          "MC": "MC",
          "MD": "ሞልዶቫ",
          "ME": "ME",
          "MF": "MF",
          "MG": "MG",
          "MH": "MH",
          "MK": "ማከዶኒያ",
          "MK-alt-variant": "MK",
          "ML": "ML",
          "MM": "MM",
          "MN": "ሞንጎሊያ",
          "MO": "ማካዎ",
          "MO-alt-short": "MO",
          "MP": "MP",
          "MQ": "MQ",
          "MR": "ሞሪቴኒያ",
          "MS": "MS",
          "MT": "ማልታ",
          "MU": "ማሩሸስ",
          "MV": "MV",
          "MW": "MW",
          "MX": "ሜክሲኮ",
          "MY": "ማሌዢያ",
          "MZ": "MZ",
          "NA": "ናሚቢያ",
          "NC": "ኒው ካሌዶኒያ",
          "NE": "NE",
          "NF": "NF",
          "NG": "ናይጄሪያ",
          "NI": "NI",
          "NL": "ኔዘርላንድ",
          "NO": "ኖርዌ",
          "NP": "ኔፓል",
          "NR": "NR",
          "NU": "NU",
          "NZ": "ኒው ዚላንድ",
          "OM": "OM",
          "PA": "PA",
          "PE": "ፔሩ",
          "PF": "የፈረንሳይ ፖሊኔዢያ",
          "PG": "ፓፑዋ ኒው ጊኒ",
          "PH": "PH",
          "PK": "PK",
          "PL": "ፖላንድ",
          "PM": "PM",
          "PN": "PN",
          "PR": "ፖርታ ሪኮ",
          "PS": "PS",
          "PS-alt-short": "PS",
          "PT": "PT",
          "PW": "PW",
          "PY": "PY",
          "QA": "QA",
          "QO": "QO",
          "RE": "RE",
          "RO": "ሮሜኒያ",
          "RS": "RS",
          "RU": "ራሺያ",
          "RW": "RW",
          "SA": "ሳውድአረቢያ",
          "SB": "SB",
          "SC": "SC",
          "SD": "ሱዳን",
          "SE": "ስዊድን",
          "SG": "ሲንጋፖር",
          "SH": "SH",
          "SI": "ስሎቬኒያ",
          "SJ": "SJ",
          "SK": "ስሎቫኪያ",
          "SL": "SL",
          "SM": "SM",
          "SN": "ሴኔጋል",
          "SO": "ሱማሌ",
          "SR": "SR",
          "SS": "SS",
          "ST": "ST",
          "SV": "SV",
          "SX": "SX",
          "SY": "ሲሪያ",
          "SZ": "SZ",
          "TA": "TA",
          "TC": "TC",
          "TD": "ቻድ",
          "TF": "የፈረንሳይ ደቡባዊ ግዛቶች",
          "TG": "TG",
          "TH": "ታይላንድ",
          "TJ": "ታጃኪስታን",
          "TK": "TK",
          "TL": "ምስራቅ ቲሞር",
          "TL-alt-variant": "TL",
          "TM": "TM",
          "TN": "ቱኒዚያ",
          "TO": "TO",
          "TR": "ቱርክ",
          "TT": "ትሪኒዳድ እና ቶባጎ",
          "TV": "TV",
          "TW": "TW",
          "TZ": "ታንዛኒያ",
          "UA": "UA",
          "UG": "ዩጋንዳ",
          "UM": "UM",
          "US": "አሜሪካ",
          "US-alt-short": "US",
          "UY": "UY",
          "UZ": "ዩዝበኪስታን",
          "VA": "VA",
          "VC": "VC",
          "VE": "ቬንዙዌላ",
          "VG": "የእንግሊዝ ድንግል ደሴቶች",
          "VI": "የአሜሪካ ቨርጂን ደሴቶች",
          "VN": "VN",
          "VU": "VU",
          "WF": "WF",
          "WS": "WS",
          "XK": "XK",
          "YE": "የመን",
          "YT": "YT",
          "ZA": "ደቡብ አፍሪካ",
          "ZM": "ዛምቢያ",
          "ZW": "ZW",
          "ZZ": "ZZ"
        }
      }
    }
  }
}
